aclients/__init__.py
aclients/aio_http_client.py
aclients/aio_mongo_client.py
aclients/aio_mysql_client.py
aclients/aio_redis_client.py
aclients/decorators.py
aclients/err_msg.py
aclients/exceptions.py
aclients/utils.py
aclients/tinylibs/__init__.py
aclients/tinylibs/blinker.py
aclients/tinylibs/tinymysql.py
aclients-1.0.1.dist-info/LICENSE
aclients-1.0.1.dist-info/METADATA
aclients-1.0.1.dist-info/WHEEL
aclients-1.0.1.dist-info/top_level.txt
aclients-1.0.1.dist-info/RECORD
