Metadata-Version: 2.1
Name: aclients
Version: 1.0.1
Summary: 基础封装库
Home-page: https://github.com/tinybees/aclients
Author: TinyBees
Author-email: a598824322@qq.com
License: MIT
Keywords: mysql,mongo,redis,http,asyncio,crud,session
Platform: UNKNOWN
Classifier: Development Status :: 4 - Beta
Classifier: Intended Audience :: Developers
Classifier: License :: OSI Approved :: MIT License
Classifier: Natural Language :: Chinese (Simplified)
Classifier: Operating System :: POSIX :: Linux
Classifier: Operating System :: Microsoft :: Windows
Classifier: Operating System :: MacOS :: MacOS X
Classifier: Topic :: Software Development :: Libraries :: Python Modules
Classifier: Topic :: Utilities
Classifier: Programming Language :: Python
Classifier: Programming Language :: Python :: 3.5
Classifier: Programming Language :: Python :: 3.6
Classifier: Programming Language :: Python :: 3.7
Classifier: Programming Language :: Python :: 3.8
Requires: sanic
Requires: aelog
Requires: aredis
Requires: hiredis
Requires: aiomysql
Requires: sqlalchemy
Requires: aiohttp
Requires: cchardet
Requires: aiodns
Requires: motor
Requires: ujson
Requires: marshmallow
Requires: PyYAML
Requires-Python: >=3.5
Requires-Dist: sanic (>=18.12)
Requires-Dist: aelog (>=1.0.3)
Requires-Dist: aredis (>=1.1.3)
Requires-Dist: hiredis
Requires-Dist: aiomysql (>=0.0.20)
Requires-Dist: sqlalchemy (>=1.2.12)
Requires-Dist: aiohttp (>=3.3.2)
Requires-Dist: cchardet
Requires-Dist: aiodns
Requires-Dist: motor (>=1.2.2)
Requires-Dist: ujson
Requires-Dist: marshmallow (>=3.0.0rc3)
Requires-Dist: PyYAML (>=3.13)
Requires-Dist: pymongo (>=3.8.0)
